CHANGELOG.txt
LICENSE.txt
MANIFEST.in
README.rst
__init__.py
setup.py
MLTSA.egg-info/PKG-INFO
MLTSA.egg-info/SOURCES.txt
MLTSA.egg-info/dependency_links.txt
MLTSA.egg-info/requires.txt
MLTSA.egg-info/top_level.txt
MLTSA_datasets/__init__.py
MLTSA_datasets/MD_DATA/__init__.py
MLTSA_datasets/MD_RUN/MD_openMM_data.py
MLTSA_datasets/MD_RUN/__init__.py
MLTSA_datasets/OneD_pot/LSTM_OneD.py
MLTSA_datasets/OneD_pot/OneD_pot_data.py
MLTSA_datasets/OneD_pot/__init__.py
MLTSA_datasets/TwoD_pot/TwoD_pot_data.py
MLTSA_datasets/TwoD_pot/__init__.py
MLTSA_sklearn/MLTSA_sk.py
MLTSA_sklearn/__init__.py
MLTSA_sklearn/models.py
MLTSA_tensorflow/MLTSA_tf.py
MLTSA_tensorflow/TF_2_LSTM.py
MLTSA_tensorflow/TF_2_MLP.py
MLTSA_tensorflow/TF_2_RNN.py
MLTSA_tensorflow/TF_old_LSTM.py
MLTSA_tensorflow/TF_old_MLP.py
MLTSA_tensorflow/__init__.py
docs/requirements.txt
docs/build/html/_sources/index.rst.txt
docs/build/html/_sources/onedfunctions.rst.txt
docs/build/html/_sources/sklearnfunctions.rst.txt
docs/build/html/_sources/tffunctions.rst.txt
docs/source/conf.py
docs/source/examples.rst
docs/source/index.rst
docs/source/onedfunctions.rst
docs/source/sklearnfunctions.rst
docs/source/summary.rst
docs/source/tffunctions.rst
docs/source/_templates/custom-class-template.rst
docs/source/_templates/custom-model-template.rst