Metadata-Version: 1.1
Name: MLTSA
Version: 0.0.4
Summary: Machine Learning Transition State Analysis
Home-page: UNKNOWN
Author: Pedro Buigues
Author-email: pedrojuanbj@gmail.com
License: MIT
Keywords: MLTSA
Platform: UNKNOWN
Classifier: Development Status :: 5 - Production/Stable
Classifier: Intended Audience :: Education
Classifier: Operating System :: Microsoft :: Windows :: Windows 10 
Classifier: License :: OSI Approved :: MIT License
Classifier: Programming Language :: Python :: 3
